{"action":{"identity":{"address":"N\u0000sourcecred\u0000core\u0000IDENTITY\u0000qhRwhreZtWiGynEPdOe4Mg\u0000","aliases":[],"id":"qhRwhreZtWiGynEPdOe4Mg","name":"system","subtype":"BOT"},"type":"CREATE_IDENTITY"},"ledgerTimestamp":1640148443567,"uuid":"liJ0SldD1sVPlazSqEa11w","version":"1"}
{"action":{"alias":{"address":"N\u0000sourcecred\u0000discourse\u0000user\u0000https://forum.acredaos.com\u0000system\u0000","description":"discourse/[@system](https://forum.acredaos.com/u/system/)"},"identityId":"qhRwhreZtWiGynEPdOe4Mg","type":"ADD_ALIAS"},"ledgerTimestamp":1640148443567,"uuid":"WimhGeV7QBPqsor6ZAsYgg","version":"1"}
{"action":{"identity":{"address":"N\u0000sourcecred\u0000core\u0000IDENTITY\u0000AoyZEtyreEkROtBSjAXZKQ\u0000","aliases":[],"id":"AoyZEtyreEkROtBSjAXZKQ","name":"acredaos","subtype":"USER"},"type":"CREATE_IDENTITY"},"ledgerTimestamp":1640148443568,"uuid":"qIRebEEXc3BSajHRRaGEaQ","version":"1"}
{"action":{"alias":{"address":"N\u0000sourcecred\u0000discourse\u0000user\u0000https://forum.acredaos.com\u0000acredaos\u0000","description":"discourse/[@acredaos](https://forum.acredaos.com/u/acredaos/)"},"identityId":"AoyZEtyreEkROtBSjAXZKQ","type":"ADD_ALIAS"},"ledgerTimestamp":1640148443568,"uuid":"kDjI2br9M3JV8Aja6orb0Q","version":"1"}
{"action":{"identity":{"address":"N\u0000sourcecred\u0000core\u0000IDENTITY\u0000DmAKaZZ0G1gzIe5e9GmLRA\u0000","aliases":[],"id":"DmAKaZZ0G1gzIe5e9GmLRA","name":"paul","subtype":"USER"},"type":"CREATE_IDENTITY"},"ledgerTimestamp":1640148443569,"uuid":"wKWZJbKm2uynq0x5DA32WA","version":"1"}
{"action":{"alias":{"address":"N\u0000sourcecred\u0000discourse\u0000user\u0000https://forum.acredaos.com\u0000paul\u0000","description":"discourse/[@paul](https://forum.acredaos.com/u/paul/)"},"identityId":"DmAKaZZ0G1gzIe5e9GmLRA","type":"ADD_ALIAS"},"ledgerTimestamp":1640148443569,"uuid":"nWvZ0k312flpyUgEl945dw","version":"1"}
{"action":{"identity":{"address":"N\u0000sourcecred\u0000core\u0000IDENTITY\u0000dO40pJDjmV59DjBrvIDocg\u0000","aliases":[],"id":"dO40pJDjmV59DjBrvIDocg","name":"SourceCred","subtype":"PROJECT"},"type":"CREATE_IDENTITY"},"ledgerTimestamp":1640148443592,"uuid":"NOkRD0PtqpEa0YF5YONaHw","version":"1"}
{"action":{"identityId":"dO40pJDjmV59DjBrvIDocg","type":"TOGGLE_ACTIVATION"},"ledgerTimestamp":1640148443592,"uuid":"hZDtJtbhPh9DnHNXDTjd0Q","version":"1"}
{"action":{"identity":{"address":"N\u0000sourcecred\u0000core\u0000IDENTITY\u0000q0L4AhNHksvagcY4O4Lcgw\u0000","aliases":[],"id":"q0L4AhNHksvagcY4O4Lcgw","name":"aia","subtype":"USER"},"type":"CREATE_IDENTITY"},"ledgerTimestamp":1662863119799,"uuid":"2BvHlGkionE5NenB4Hxxkg","version":"1"}
{"action":{"alias":{"address":"N\u0000sourcecred\u0000discourse\u0000user\u0000https://forum.acredaos.com\u0000aia\u0000","description":"discourse/[@aia](https://forum.acredaos.com/u/aia/)"},"identityId":"q0L4AhNHksvagcY4O4Lcgw","type":"ADD_ALIAS"},"ledgerTimestamp":1662863119800,"uuid":"Bxv1Jtb3q7MyVgZy62INCQ","version":"1"}
{"action":{"identity":{"address":"N\u0000sourcecred\u0000core\u0000IDENTITY\u0000Q7imRbiGx6YKyreg7DQzEA\u0000","aliases":[],"id":"Q7imRbiGx6YKyreg7DQzEA","name":"kianga","subtype":"USER"},"type":"CREATE_IDENTITY"},"ledgerTimestamp":1662863119801,"uuid":"tPDLdzztoRBElV7waTKfqw","version":"1"}
{"action":{"alias":{"address":"N\u0000sourcecred\u0000discourse\u0000user\u0000https://forum.acredaos.com\u0000kianga\u0000","description":"discourse/[@kianga](https://forum.acredaos.com/u/kianga/)"},"identityId":"Q7imRbiGx6YKyreg7DQzEA","type":"ADD_ALIAS"},"ledgerTimestamp":1662863119802,"uuid":"RS293IKRYLOJKRvFE8bBqg","version":"1"}
{"action":{"distribution":{"allocations":[{"id":"KewJy7nvG6DOMBasbUlpVw","policy":{"budget":"450000000000000000000","discount":0.5,"exclusions":[],"policyType":"RECENT"},"receipts":[{"amount":"450000000000000000000","id":"dO40pJDjmV59DjBrvIDocg"}]}],"credTimestamp":1637452800000,"id":"rX1iyZgdSeGOuBaLmmcmkg"},"type":"DISTRIBUTE_GRAIN"},"ledgerTimestamp":1662863120621,"uuid":"0MfyKiRBxa8uER7yIrJwyg","version":"1"}
{"action":{"distribution":{"allocations":[{"id":"efPve60EaOm4gNYB4cRDug","policy":{"budget":"450000000000000000000","discount":0.5,"exclusions":[],"policyType":"RECENT"},"receipts":[{"amount":"450000000000000000000","id":"dO40pJDjmV59DjBrvIDocg"}]}],"credTimestamp":1638057600000,"id":"q4tXxNA8idMc5Whq7dKMew"},"type":"DISTRIBUTE_GRAIN"},"ledgerTimestamp":1662863120630,"uuid":"MmhyQRsjyiZNfDCKzZMPNw","version":"1"}
{"action":{"distribution":{"allocations":[{"id":"BVoZTLsQtlE1WC1wbTXQ5g","policy":{"budget":"450000000000000000000","discount":0.5,"exclusions":[],"policyType":"RECENT"},"receipts":[{"amount":"450000000000000000000","id":"dO40pJDjmV59DjBrvIDocg"}]}],"credTimestamp":1638662400000,"id":"UYVaL7S2Mo67cdAm2UeQag"},"type":"DISTRIBUTE_GRAIN"},"ledgerTimestamp":1662863120636,"uuid":"d08X6JcYWO5rVKpKT5ptKQ","version":"1"}
{"action":{"distribution":{"allocations":[{"id":"Ami07H83U1K3oDJKNuLFLQ","policy":{"budget":"450000000000000000000","discount":0.5,"exclusions":[],"policyType":"RECENT"},"receipts":[{"amount":"450000000000000000000","id":"dO40pJDjmV59DjBrvIDocg"}]}],"credTimestamp":1639267200000,"id":"l3MfDxrl6yOpuMjRya696A"},"type":"DISTRIBUTE_GRAIN"},"ledgerTimestamp":1662863120640,"uuid":"TVfaeat1kxeUOnnQXfOXKQ","version":"1"}
{"action":{"distribution":{"allocations":[{"id":"tGXHJ3S4Y7rcan5n92W6uw","policy":{"budget":"450000000000000000000","discount":0.5,"exclusions":[],"policyType":"RECENT"},"receipts":[{"amount":"450000000000000000000","id":"dO40pJDjmV59DjBrvIDocg"}]}],"credTimestamp":1639872000000,"id":"3fwsW4ehDxFEi4H6kvA7Yw"},"type":"DISTRIBUTE_GRAIN"},"ledgerTimestamp":1662863120645,"uuid":"0C0U3my2bSKY3WdZR9xuqA","version":"1"}
{"action":{"distribution":{"allocations":[{"id":"x39pJmYTehzW98nQGzkgpQ","policy":{"budget":"450000000000000000000","discount":0.5,"exclusions":[],"policyType":"RECENT"},"receipts":[{"amount":"450000000000000000000","id":"dO40pJDjmV59DjBrvIDocg"}]}],"credTimestamp":1640476800000,"id":"SYlTgSXfoVZbu7y3GwETbA"},"type":"DISTRIBUTE_GRAIN"},"ledgerTimestamp":1662863120649,"uuid":"aKm03VOHEwmPgwrWiqvwkw","version":"1"}
{"action":{"distribution":{"allocations":[{"id":"0geXd0Ae0BopDxw30fvwTQ","policy":{"budget":"450000000000000000000","discount":0.5,"exclusions":[],"policyType":"RECENT"},"receipts":[{"amount":"450000000000000000000","id":"dO40pJDjmV59DjBrvIDocg"}]}],"credTimestamp":1641081600000,"id":"5BxwP2ExC6Uduo8Fo0Pddg"},"type":"DISTRIBUTE_GRAIN"},"ledgerTimestamp":1662863120654,"uuid":"kRGIDYwVPC9NYQjuDS78fw","version":"1"}
{"action":{"distribution":{"allocations":[{"id":"gJJfZ7jTM3qfpZgpYaB1bA","policy":{"budget":"450000000000000000000","discount":0.5,"exclusions":[],"policyType":"RECENT"},"receipts":[{"amount":"450000000000000000000","id":"dO40pJDjmV59DjBrvIDocg"}]}],"credTimestamp":1641686400000,"id":"N0sb0qnPgMLV3qdIWQwlMg"},"type":"DISTRIBUTE_GRAIN"},"ledgerTimestamp":1662863120658,"uuid":"hg46u47JgZRkVLD1eekCGg","version":"1"}
{"action":{"distribution":{"allocations":[{"id":"T0i7Vdjd49W41et2KPXl7A","policy":{"budget":"450000000000000000000","discount":0.5,"exclusions":[],"policyType":"RECENT"},"receipts":[{"amount":"450000000000000000000","id":"dO40pJDjmV59DjBrvIDocg"}]}],"credTimestamp":1642291200000,"id":"5Zaq8LXU1Q6X1hbZPYDgWQ"},"type":"DISTRIBUTE_GRAIN"},"ledgerTimestamp":1662863120662,"uuid":"RkowhLnobt2Kf4KJyX4hLg","version":"1"}
{"action":{"distribution":{"allocations":[{"id":"ncLavYW3nYrLIjx8Mb9WvA","policy":{"budget":"450000000000000000000","discount":0.5,"exclusions":[],"policyType":"RECENT"},"receipts":[{"amount":"450000000000000000000","id":"dO40pJDjmV59DjBrvIDocg"}]}],"credTimestamp":1642896000000,"id":"RQ24lAU7hJyCRTN72Jh04w"},"type":"DISTRIBUTE_GRAIN"},"ledgerTimestamp":1662863120665,"uuid":"Ks21MhZYuB7XR063cWk0pA","version":"1"}
{"action":{"distribution":{"allocations":[{"id":"jL35Z0duKYyZZEZ9qls1SQ","policy":{"budget":"450000000000000000000","discount":0.5,"exclusions":[],"policyType":"RECENT"},"receipts":[{"amount":"450000000000000000000","id":"dO40pJDjmV59DjBrvIDocg"}]}],"credTimestamp":1643500800000,"id":"UbCGPiqrGZoircqqjRlXAA"},"type":"DISTRIBUTE_GRAIN"},"ledgerTimestamp":1662863120669,"uuid":"tY0uw2YCD7yLHKLcmX5FWA","version":"1"}
{"action":{"distribution":{"allocations":[{"id":"9oqsaTLtBpH2HQKMMlKnvQ","policy":{"budget":"450000000000000000000","discount":0.5,"exclusions":[],"policyType":"RECENT"},"receipts":[{"amount":"450000000000000000000","id":"dO40pJDjmV59DjBrvIDocg"}]}],"credTimestamp":1644105600000,"id":"NY4whgUmfp8uB4JJ45dnkg"},"type":"DISTRIBUTE_GRAIN"},"ledgerTimestamp":1662863120674,"uuid":"KmpGG8Mm5K3aGgRbo7lTGQ","version":"1"}
{"action":{"distribution":{"allocations":[{"id":"kbxky6CphBY7ujPnFbcNUw","policy":{"budget":"450000000000000000000","discount":0.5,"exclusions":[],"policyType":"RECENT"},"receipts":[{"amount":"450000000000000000000","id":"dO40pJDjmV59DjBrvIDocg"}]}],"credTimestamp":1644710400000,"id":"8AAUJjPwKq7Y5ng0BY7CxQ"},"type":"DISTRIBUTE_GRAIN"},"ledgerTimestamp":1662863120682,"uuid":"TOgCoGCl8jC8kabC9CqlWg","version":"1"}
{"action":{"distribution":{"allocations":[{"id":"N0E4vQzdZPQZbIWpEC2NlA","policy":{"budget":"450000000000000000000","discount":0.5,"exclusions":[],"policyType":"RECENT"},"receipts":[{"amount":"450000000000000000000","id":"dO40pJDjmV59DjBrvIDocg"}]}],"credTimestamp":1645315200000,"id":"QAjxlZYiG4zqUvcWqbPsGQ"},"type":"DISTRIBUTE_GRAIN"},"ledgerTimestamp":1662863120694,"uuid":"27MVLKYMAek4vdPFxwBZPw","version":"1"}
{"action":{"distribution":{"allocations":[{"id":"rdak48qrkkBjVJqn7hP1iw","policy":{"budget":"450000000000000000000","discount":0.5,"exclusions":[],"policyType":"RECENT"},"receipts":[{"amount":"450000000000000000000","id":"dO40pJDjmV59DjBrvIDocg"}]}],"credTimestamp":1645920000000,"id":"vqlp4WoK4DL5PCZGAUpjEg"},"type":"DISTRIBUTE_GRAIN"},"ledgerTimestamp":1662863120697,"uuid":"L10E67RS5niE1J75gyW63Q","version":"1"}
{"action":{"distribution":{"allocations":[{"id":"0REFjOj48PHlWILO6AniqA","policy":{"budget":"450000000000000000000","discount":0.5,"exclusions":[],"policyType":"RECENT"},"receipts":[{"amount":"450000000000000000000","id":"dO40pJDjmV59DjBrvIDocg"}]}],"credTimestamp":1646524800000,"id":"avyUpGclB0XC3mALvLAbKw"},"type":"DISTRIBUTE_GRAIN"},"ledgerTimestamp":1662863120700,"uuid":"bdWxW1w0tnDuaX9TZK7bFw","version":"1"}
{"action":{"distribution":{"allocations":[{"id":"6k25qnLpBdeSwhVk0u5Zyw","policy":{"budget":"450000000000000000000","discount":0.5,"exclusions":[],"policyType":"RECENT"},"receipts":[{"amount":"450000000000000000000","id":"dO40pJDjmV59DjBrvIDocg"}]}],"credTimestamp":1647129600000,"id":"8elzHmnGtMaG56e3Oy6JQg"},"type":"DISTRIBUTE_GRAIN"},"ledgerTimestamp":1662863120703,"uuid":"j7tGtqOYqotNlWsM2dzaoQ","version":"1"}
{"action":{"distribution":{"allocations":[{"id":"nPy2xmVDVd1ggI7NdVHJuA","policy":{"budget":"450000000000000000000","discount":0.5,"exclusions":[],"policyType":"RECENT"},"receipts":[{"amount":"450000000000000000000","id":"dO40pJDjmV59DjBrvIDocg"}]}],"credTimestamp":1647734400000,"id":"F3BWRdEAJS2HzxxL8XlkmA"},"type":"DISTRIBUTE_GRAIN"},"ledgerTimestamp":1662863120707,"uuid":"vjhx1AVFjtMlXQGZrWuxpw","version":"1"}
{"action":{"distribution":{"allocations":[{"id":"i77ping4oHWyrUMPeLWb7g","policy":{"budget":"450000000000000000000","discount":0.5,"exclusions":[],"policyType":"RECENT"},"receipts":[{"amount":"450000000000000000000","id":"dO40pJDjmV59DjBrvIDocg"}]}],"credTimestamp":1648339200000,"id":"JdJ1jqY11AM08GAWPZdprw"},"type":"DISTRIBUTE_GRAIN"},"ledgerTimestamp":1662863120712,"uuid":"xGqtXSzwAWWEyqbWnMYbxQ","version":"1"}
{"action":{"distribution":{"allocations":[{"id":"BS3ACgWPPqdsoqHO3MOazQ","policy":{"budget":"450000000000000000000","discount":0.5,"exclusions":[],"policyType":"RECENT"},"receipts":[{"amount":"450000000000000000000","id":"dO40pJDjmV59DjBrvIDocg"}]}],"credTimestamp":1648944000000,"id":"8O8zpClsDkEwjVuk89kpkw"},"type":"DISTRIBUTE_GRAIN"},"ledgerTimestamp":1662863120714,"uuid":"mdhykjq5axEGnjswQ2q1Gg","version":"1"}
{"action":{"distribution":{"allocations":[{"id":"3tYXrsowjq2WVjJ1ELNHXQ","policy":{"budget":"450000000000000000000","discount":0.5,"exclusions":[],"policyType":"RECENT"},"receipts":[{"amount":"450000000000000000000","id":"dO40pJDjmV59DjBrvIDocg"}]}],"credTimestamp":1649548800000,"id":"Y0xZrvMCbx66BeOObIWMDg"},"type":"DISTRIBUTE_GRAIN"},"ledgerTimestamp":1662863120718,"uuid":"2l3idwinAC334bpjNe0JUQ","version":"1"}
{"action":{"distribution":{"allocations":[{"id":"F8YpJLyimaV7mPKEqueC3g","policy":{"budget":"450000000000000000000","discount":0.5,"exclusions":[],"policyType":"RECENT"},"receipts":[{"amount":"450000000000000000000","id":"dO40pJDjmV59DjBrvIDocg"}]}],"credTimestamp":1650153600000,"id":"ME1c5gcpn5JEheea42vvYA"},"type":"DISTRIBUTE_GRAIN"},"ledgerTimestamp":1662863120721,"uuid":"ZGpc8d20VJnn2dZ83zc3hg","version":"1"}
{"action":{"distribution":{"allocations":[{"id":"js1GkdPn35ty9bbbkjzYZA","policy":{"budget":"450000000000000000000","discount":0.5,"exclusions":[],"policyType":"RECENT"},"receipts":[{"amount":"450000000000000000000","id":"dO40pJDjmV59DjBrvIDocg"}]}],"credTimestamp":1650758400000,"id":"889PjfJrm2ApR4v4tPjqsA"},"type":"DISTRIBUTE_GRAIN"},"ledgerTimestamp":1662863120724,"uuid":"Y5PEZK0jgAU5UeVQg8G7Nw","version":"1"}
{"action":{"distribution":{"allocations":[{"id":"wUkFPeyDlNKd4uwaAhlI4Q","policy":{"budget":"450000000000000000000","discount":0.5,"exclusions":[],"policyType":"RECENT"},"receipts":[{"amount":"450000000000000000000","id":"dO40pJDjmV59DjBrvIDocg"}]}],"credTimestamp":1651363200000,"id":"715OE6u39GqJZNqj00n56g"},"type":"DISTRIBUTE_GRAIN"},"ledgerTimestamp":1662863120727,"uuid":"jZCgM9ASQunYzBgDi97lrw","version":"1"}
{"action":{"distribution":{"allocations":[{"id":"qcLAPi46EQ68wh5ueBFagw","policy":{"budget":"450000000000000000000","discount":0.5,"exclusions":[],"policyType":"RECENT"},"receipts":[{"amount":"450000000000000000000","id":"dO40pJDjmV59DjBrvIDocg"}]}],"credTimestamp":1651968000000,"id":"yJBHmk71otRRh2AJU1w3Ug"},"type":"DISTRIBUTE_GRAIN"},"ledgerTimestamp":1662863120729,"uuid":"rNlC7KJLE5i1o1iyVFjxkQ","version":"1"}
{"action":{"distribution":{"allocations":[{"id":"MjTEbDVB7984bhpdx8ZqRQ","policy":{"budget":"450000000000000000000","discount":0.5,"exclusions":[],"policyType":"RECENT"},"receipts":[{"amount":"450000000000000000000","id":"dO40pJDjmV59DjBrvIDocg"}]}],"credTimestamp":1652572800000,"id":"UZt9E5xbyyB73L7nn4LSeQ"},"type":"DISTRIBUTE_GRAIN"},"ledgerTimestamp":1662863120733,"uuid":"nU9nyoDNDI6b4IMg77bCdA","version":"1"}
{"action":{"distribution":{"allocations":[{"id":"aE2ibbm8nr4X4W1tZ9nGhQ","policy":{"budget":"450000000000000000000","discount":0.5,"exclusions":[],"policyType":"RECENT"},"receipts":[{"amount":"450000000000000000000","id":"dO40pJDjmV59DjBrvIDocg"}]}],"credTimestamp":1653177600000,"id":"c7l1AA9D3bji3WyRs96Sag"},"type":"DISTRIBUTE_GRAIN"},"ledgerTimestamp":1662863120735,"uuid":"0H6ho0cpukRjZOghwZ0WhA","version":"1"}
{"action":{"distribution":{"allocations":[{"id":"zEpyWq18CODBloHVYEMF4A","policy":{"budget":"450000000000000000000","discount":0.5,"exclusions":[],"policyType":"RECENT"},"receipts":[{"amount":"450000000000000000000","id":"dO40pJDjmV59DjBrvIDocg"}]}],"credTimestamp":1653782400000,"id":"JvU80TAFbwb2yf5Ppe2DjQ"},"type":"DISTRIBUTE_GRAIN"},"ledgerTimestamp":1662863120739,"uuid":"pABCQQyhL1nPbSGykmzZTw","version":"1"}
