{"action":{"identity":{"address":"N\u0000sourcecred\u0000core\u0000IDENTITY\u0000qhRwhreZtWiGynEPdOe4Mg\u0000","aliases":[],"id":"qhRwhreZtWiGynEPdOe4Mg","name":"system","subtype":"BOT"},"type":"CREATE_IDENTITY"},"ledgerTimestamp":1640148443567,"uuid":"liJ0SldD1sVPlazSqEa11w","version":"1"}
{"action":{"alias":{"address":"N\u0000sourcecred\u0000discourse\u0000user\u0000https://forum.acredaos.com\u0000system\u0000","description":"discourse/[@system](https://forum.acredaos.com/u/system/)"},"identityId":"qhRwhreZtWiGynEPdOe4Mg","type":"ADD_ALIAS"},"ledgerTimestamp":1640148443567,"uuid":"WimhGeV7QBPqsor6ZAsYgg","version":"1"}
{"action":{"identity":{"address":"N\u0000sourcecred\u0000core\u0000IDENTITY\u0000AoyZEtyreEkROtBSjAXZKQ\u0000","aliases":[],"id":"AoyZEtyreEkROtBSjAXZKQ","name":"acredaos","subtype":"USER"},"type":"CREATE_IDENTITY"},"ledgerTimestamp":1640148443568,"uuid":"qIRebEEXc3BSajHRRaGEaQ","version":"1"}
{"action":{"alias":{"address":"N\u0000sourcecred\u0000discourse\u0000user\u0000https://forum.acredaos.com\u0000acredaos\u0000","description":"discourse/[@acredaos](https://forum.acredaos.com/u/acredaos/)"},"identityId":"AoyZEtyreEkROtBSjAXZKQ","type":"ADD_ALIAS"},"ledgerTimestamp":1640148443568,"uuid":"kDjI2br9M3JV8Aja6orb0Q","version":"1"}
{"action":{"identity":{"address":"N\u0000sourcecred\u0000core\u0000IDENTITY\u0000DmAKaZZ0G1gzIe5e9GmLRA\u0000","aliases":[],"id":"DmAKaZZ0G1gzIe5e9GmLRA","name":"paul","subtype":"USER"},"type":"CREATE_IDENTITY"},"ledgerTimestamp":1640148443569,"uuid":"wKWZJbKm2uynq0x5DA32WA","version":"1"}
{"action":{"alias":{"address":"N\u0000sourcecred\u0000discourse\u0000user\u0000https://forum.acredaos.com\u0000paul\u0000","description":"discourse/[@paul](https://forum.acredaos.com/u/paul/)"},"identityId":"DmAKaZZ0G1gzIe5e9GmLRA","type":"ADD_ALIAS"},"ledgerTimestamp":1640148443569,"uuid":"nWvZ0k312flpyUgEl945dw","version":"1"}
{"action":{"identity":{"address":"N\u0000sourcecred\u0000core\u0000IDENTITY\u0000dO40pJDjmV59DjBrvIDocg\u0000","aliases":[],"id":"dO40pJDjmV59DjBrvIDocg","name":"SourceCred","subtype":"PROJECT"},"type":"CREATE_IDENTITY"},"ledgerTimestamp":1640148443592,"uuid":"NOkRD0PtqpEa0YF5YONaHw","version":"1"}
{"action":{"identityId":"dO40pJDjmV59DjBrvIDocg","type":"TOGGLE_ACTIVATION"},"ledgerTimestamp":1640148443592,"uuid":"hZDtJtbhPh9DnHNXDTjd0Q","version":"1"}
{"action":{"identity":{"address":"N\u0000sourcecred\u0000core\u0000IDENTITY\u00008Vb6MTquoREZHXtylGGm0g\u0000","aliases":[],"id":"8Vb6MTquoREZHXtylGGm0g","name":"aia","subtype":"USER"},"type":"CREATE_IDENTITY"},"ledgerTimestamp":1659233848791,"uuid":"FNTDkVHmjudcDvO0JsAxEg","version":"1"}
{"action":{"alias":{"address":"N\u0000sourcecred\u0000discourse\u0000user\u0000https://forum.acredaos.com\u0000aia\u0000","description":"discourse/[@aia](https://forum.acredaos.com/u/aia/)"},"identityId":"8Vb6MTquoREZHXtylGGm0g","type":"ADD_ALIAS"},"ledgerTimestamp":1659233848791,"uuid":"lecxnvq5Jmm4BRvt1CQfJw","version":"1"}
{"action":{"identity":{"address":"N\u0000sourcecred\u0000core\u0000IDENTITY\u0000UaLs2t9MWnbKI0jy02cyhg\u0000","aliases":[],"id":"UaLs2t9MWnbKI0jy02cyhg","name":"kianga","subtype":"USER"},"type":"CREATE_IDENTITY"},"ledgerTimestamp":1659233848792,"uuid":"AqYgfYLCYKtkAF8aqmRxfA","version":"1"}
{"action":{"alias":{"address":"N\u0000sourcecred\u0000discourse\u0000user\u0000https://forum.acredaos.com\u0000kianga\u0000","description":"discourse/[@kianga](https://forum.acredaos.com/u/kianga/)"},"identityId":"UaLs2t9MWnbKI0jy02cyhg","type":"ADD_ALIAS"},"ledgerTimestamp":1659233848792,"uuid":"yEbrSjPyf7gcgBuyrzcWMQ","version":"1"}
{"action":{"distribution":{"allocations":[{"id":"Jzi3XK5B2WkZiXpD6A0WjA","policy":{"budget":"450000000000000000000","discount":0.5,"exclusions":[],"policyType":"RECENT"},"receipts":[{"amount":"450000000000000000000","id":"dO40pJDjmV59DjBrvIDocg"}]}],"credTimestamp":1637452800000,"id":"dK4O3mGnqYVE4g8PoLvR7Q"},"type":"DISTRIBUTE_GRAIN"},"ledgerTimestamp":1659233849686,"uuid":"hmlVGjmfdmxcE577SBTqLQ","version":"1"}
{"action":{"distribution":{"allocations":[{"id":"Nk3zapUdI6q2QRXsefpswA","policy":{"budget":"450000000000000000000","discount":0.5,"exclusions":[],"policyType":"RECENT"},"receipts":[{"amount":"450000000000000000000","id":"dO40pJDjmV59DjBrvIDocg"}]}],"credTimestamp":1638057600000,"id":"GCOVHmk701oAG6WdDJY8mg"},"type":"DISTRIBUTE_GRAIN"},"ledgerTimestamp":1659233849692,"uuid":"9FL8c1C6HzQjkRpJTkzdrw","version":"1"}
{"action":{"distribution":{"allocations":[{"id":"sVW6oRQW2y8UdJj2xtNmSw","policy":{"budget":"450000000000000000000","discount":0.5,"exclusions":[],"policyType":"RECENT"},"receipts":[{"amount":"450000000000000000000","id":"dO40pJDjmV59DjBrvIDocg"}]}],"credTimestamp":1638662400000,"id":"UyPw67VryPlGMJcB4dtJfg"},"type":"DISTRIBUTE_GRAIN"},"ledgerTimestamp":1659233849701,"uuid":"qULdnkm82pi3gv2sNoBqDQ","version":"1"}
{"action":{"distribution":{"allocations":[{"id":"FR8geTRvRk3r2ZMllNjUmw","policy":{"budget":"450000000000000000000","discount":0.5,"exclusions":[],"policyType":"RECENT"},"receipts":[{"amount":"450000000000000000000","id":"dO40pJDjmV59DjBrvIDocg"}]}],"credTimestamp":1639267200000,"id":"ar6ytN8UpCahAr1MhOPwNg"},"type":"DISTRIBUTE_GRAIN"},"ledgerTimestamp":1659233849705,"uuid":"Fq8fRdoCgwV4SN6i2nkH8g","version":"1"}
{"action":{"distribution":{"allocations":[{"id":"aaAArJTZXA41yRC7mRiVMg","policy":{"budget":"450000000000000000000","discount":0.5,"exclusions":[],"policyType":"RECENT"},"receipts":[{"amount":"450000000000000000000","id":"dO40pJDjmV59DjBrvIDocg"}]}],"credTimestamp":1639872000000,"id":"3qvzrP2sKYbyPnAe1KVABw"},"type":"DISTRIBUTE_GRAIN"},"ledgerTimestamp":1659233849711,"uuid":"5DUZDRcDfVKdGw10yco6gg","version":"1"}
{"action":{"distribution":{"allocations":[{"id":"DrvrMiQ0mIKx3EpKGMWZLg","policy":{"budget":"450000000000000000000","discount":0.5,"exclusions":[],"policyType":"RECENT"},"receipts":[{"amount":"450000000000000000000","id":"dO40pJDjmV59DjBrvIDocg"}]}],"credTimestamp":1640476800000,"id":"65c394ehabAtkKteMlW7ag"},"type":"DISTRIBUTE_GRAIN"},"ledgerTimestamp":1659233849716,"uuid":"FN2RROmp2APyqVBHJgPb3w","version":"1"}
{"action":{"distribution":{"allocations":[{"id":"KLLRExT9i9xw4ubvMEaurA","policy":{"budget":"450000000000000000000","discount":0.5,"exclusions":[],"policyType":"RECENT"},"receipts":[{"amount":"450000000000000000000","id":"dO40pJDjmV59DjBrvIDocg"}]}],"credTimestamp":1641081600000,"id":"rD6zerLnTjKnQ2edg1n5vg"},"type":"DISTRIBUTE_GRAIN"},"ledgerTimestamp":1659233849720,"uuid":"lVNOgk8MPiWdHp97rBC1ug","version":"1"}
{"action":{"distribution":{"allocations":[{"id":"XnbqsG207G2Zl2qc5pb6bw","policy":{"budget":"450000000000000000000","discount":0.5,"exclusions":[],"policyType":"RECENT"},"receipts":[{"amount":"450000000000000000000","id":"dO40pJDjmV59DjBrvIDocg"}]}],"credTimestamp":1641686400000,"id":"0DdTVj3zNFognr3CRSnnLA"},"type":"DISTRIBUTE_GRAIN"},"ledgerTimestamp":1659233849725,"uuid":"bwU64c9bRJv6IBooSMD9IQ","version":"1"}
{"action":{"distribution":{"allocations":[{"id":"TnyKoq9w7Y8VxEcRvrFYeQ","policy":{"budget":"450000000000000000000","discount":0.5,"exclusions":[],"policyType":"RECENT"},"receipts":[{"amount":"450000000000000000000","id":"dO40pJDjmV59DjBrvIDocg"}]}],"credTimestamp":1642291200000,"id":"rJO2tB2qurKR1eRRtKWHxA"},"type":"DISTRIBUTE_GRAIN"},"ledgerTimestamp":1659233849729,"uuid":"HE6TQUgzbDTeN5rlrt8rqw","version":"1"}
{"action":{"distribution":{"allocations":[{"id":"U6wgqu5ZRuR5VzZcEXNbIw","policy":{"budget":"450000000000000000000","discount":0.5,"exclusions":[],"policyType":"RECENT"},"receipts":[{"amount":"450000000000000000000","id":"dO40pJDjmV59DjBrvIDocg"}]}],"credTimestamp":1642896000000,"id":"XuOWyliwBQckIa7dgPmD3w"},"type":"DISTRIBUTE_GRAIN"},"ledgerTimestamp":1659233849733,"uuid":"j6KcO2t5LjEnggWVDjUWgg","version":"1"}
{"action":{"distribution":{"allocations":[{"id":"YacAhnJxIAOmfpWBZtyPew","policy":{"budget":"450000000000000000000","discount":0.5,"exclusions":[],"policyType":"RECENT"},"receipts":[{"amount":"450000000000000000000","id":"dO40pJDjmV59DjBrvIDocg"}]}],"credTimestamp":1643500800000,"id":"3lGdltmadW9IQYerDtDw5w"},"type":"DISTRIBUTE_GRAIN"},"ledgerTimestamp":1659233849737,"uuid":"Iy8XvWZ1qme1rTeH4RotdQ","version":"1"}
{"action":{"distribution":{"allocations":[{"id":"D5AGr5IwdW1djw2QTAJNVA","policy":{"budget":"450000000000000000000","discount":0.5,"exclusions":[],"policyType":"RECENT"},"receipts":[{"amount":"450000000000000000000","id":"dO40pJDjmV59DjBrvIDocg"}]}],"credTimestamp":1644105600000,"id":"FK4hYqQ1XohKhxzzxTEdUQ"},"type":"DISTRIBUTE_GRAIN"},"ledgerTimestamp":1659233849743,"uuid":"UkIV4Gt6lMZZ5GKmnavGOA","version":"1"}
{"action":{"distribution":{"allocations":[{"id":"6H91lBzy7mMjeXr6za51jQ","policy":{"budget":"450000000000000000000","discount":0.5,"exclusions":[],"policyType":"RECENT"},"receipts":[{"amount":"450000000000000000000","id":"dO40pJDjmV59DjBrvIDocg"}]}],"credTimestamp":1644710400000,"id":"DMy6LlQd18tjV13UY8GUOQ"},"type":"DISTRIBUTE_GRAIN"},"ledgerTimestamp":1659233849750,"uuid":"2w0NeC3trEd92RoAhx98tg","version":"1"}
{"action":{"distribution":{"allocations":[{"id":"7mmyhY1wwTwT2kpqmUVJnw","policy":{"budget":"450000000000000000000","discount":0.5,"exclusions":[],"policyType":"RECENT"},"receipts":[{"amount":"450000000000000000000","id":"dO40pJDjmV59DjBrvIDocg"}]}],"credTimestamp":1645315200000,"id":"KDtpnmxXNzfP35wOv2VwMQ"},"type":"DISTRIBUTE_GRAIN"},"ledgerTimestamp":1659233849757,"uuid":"pzjU9BZDP3ULGud1Kpl12Q","version":"1"}
{"action":{"distribution":{"allocations":[{"id":"ZHyRUKs0ioxc33Jm9hDBlQ","policy":{"budget":"450000000000000000000","discount":0.5,"exclusions":[],"policyType":"RECENT"},"receipts":[{"amount":"450000000000000000000","id":"dO40pJDjmV59DjBrvIDocg"}]}],"credTimestamp":1645920000000,"id":"gVq43vVwNFodPue8pHLyHg"},"type":"DISTRIBUTE_GRAIN"},"ledgerTimestamp":1659233849760,"uuid":"7TGJ1yr0DnvHdtvmqVGiRA","version":"1"}
{"action":{"distribution":{"allocations":[{"id":"Jf96Rlol3spTovxwK1gcYg","policy":{"budget":"450000000000000000000","discount":0.5,"exclusions":[],"policyType":"RECENT"},"receipts":[{"amount":"450000000000000000000","id":"dO40pJDjmV59DjBrvIDocg"}]}],"credTimestamp":1646524800000,"id":"hqejgTaTLUkHd9OPGc8Z3g"},"type":"DISTRIBUTE_GRAIN"},"ledgerTimestamp":1659233849764,"uuid":"O3JhbNI24flnn3afdrVmeA","version":"1"}
{"action":{"distribution":{"allocations":[{"id":"6fGPv8ijbYK5FEEWwCWgPg","policy":{"budget":"450000000000000000000","discount":0.5,"exclusions":[],"policyType":"RECENT"},"receipts":[{"amount":"450000000000000000000","id":"dO40pJDjmV59DjBrvIDocg"}]}],"credTimestamp":1647129600000,"id":"mcxJPxtrUKi3L175g4LUXg"},"type":"DISTRIBUTE_GRAIN"},"ledgerTimestamp":1659233849767,"uuid":"ZoowrOQ4R8ktOA0nUrKPwQ","version":"1"}
{"action":{"distribution":{"allocations":[{"id":"DLHamtr8Py9KjjPELPgoNg","policy":{"budget":"450000000000000000000","discount":0.5,"exclusions":[],"policyType":"RECENT"},"receipts":[{"amount":"450000000000000000000","id":"dO40pJDjmV59DjBrvIDocg"}]}],"credTimestamp":1647734400000,"id":"Q8ll3fnOaa1Vnxz8GSvSWA"},"type":"DISTRIBUTE_GRAIN"},"ledgerTimestamp":1659233849772,"uuid":"NxIqKO69myVidbnIOesBfw","version":"1"}
{"action":{"distribution":{"allocations":[{"id":"gMiaarUaOwDn0vDR9h27Iw","policy":{"budget":"450000000000000000000","discount":0.5,"exclusions":[],"policyType":"RECENT"},"receipts":[{"amount":"450000000000000000000","id":"dO40pJDjmV59DjBrvIDocg"}]}],"credTimestamp":1648339200000,"id":"aa8pmDcXWPZXOfBTbtmbVg"},"type":"DISTRIBUTE_GRAIN"},"ledgerTimestamp":1659233849776,"uuid":"XFw8Drzv2l1xRnlV9Fn3dQ","version":"1"}
{"action":{"distribution":{"allocations":[{"id":"hLyFzfbXnNzPNgtLoLOZIw","policy":{"budget":"450000000000000000000","discount":0.5,"exclusions":[],"policyType":"RECENT"},"receipts":[{"amount":"450000000000000000000","id":"dO40pJDjmV59DjBrvIDocg"}]}],"credTimestamp":1648944000000,"id":"zd11nHP0oVeJvEUejDUJ4Q"},"type":"DISTRIBUTE_GRAIN"},"ledgerTimestamp":1659233849779,"uuid":"ZLy7aV06s3erQKGdzmujWw","version":"1"}
{"action":{"distribution":{"allocations":[{"id":"ONEP3iDbAnRElZtlVUZqCw","policy":{"budget":"450000000000000000000","discount":0.5,"exclusions":[],"policyType":"RECENT"},"receipts":[{"amount":"450000000000000000000","id":"dO40pJDjmV59DjBrvIDocg"}]}],"credTimestamp":1649548800000,"id":"QmbY2JXFBWZNGTq4MdeoZg"},"type":"DISTRIBUTE_GRAIN"},"ledgerTimestamp":1659233849784,"uuid":"tYDasGXdQfYQRU09rXbgUg","version":"1"}
{"action":{"distribution":{"allocations":[{"id":"jyzWSpDKn9XblQcVj2OYVg","policy":{"budget":"450000000000000000000","discount":0.5,"exclusions":[],"policyType":"RECENT"},"receipts":[{"amount":"450000000000000000000","id":"dO40pJDjmV59DjBrvIDocg"}]}],"credTimestamp":1650153600000,"id":"WKo4p8xCeIEbMFMx90gy3g"},"type":"DISTRIBUTE_GRAIN"},"ledgerTimestamp":1659233849788,"uuid":"A4GovpbE769aERwTNkqDZg","version":"1"}
{"action":{"distribution":{"allocations":[{"id":"uR1X7eQQKAkRmlD1XR2qGA","policy":{"budget":"450000000000000000000","discount":0.5,"exclusions":[],"policyType":"RECENT"},"receipts":[{"amount":"450000000000000000000","id":"dO40pJDjmV59DjBrvIDocg"}]}],"credTimestamp":1650758400000,"id":"BnUXJdDFRJdtdqKlMFQydw"},"type":"DISTRIBUTE_GRAIN"},"ledgerTimestamp":1659233849790,"uuid":"LPjEdfgakDwrgcgT3LiO3Q","version":"1"}
{"action":{"distribution":{"allocations":[{"id":"kG1c5qgNbA7oZ4FoqOHpdg","policy":{"budget":"450000000000000000000","discount":0.5,"exclusions":[],"policyType":"RECENT"},"receipts":[{"amount":"450000000000000000000","id":"dO40pJDjmV59DjBrvIDocg"}]}],"credTimestamp":1651363200000,"id":"mIORWXIbHOZ2f77KMhaOhg"},"type":"DISTRIBUTE_GRAIN"},"ledgerTimestamp":1659233849794,"uuid":"R20xzXwZw1ToCxNWg6QYuQ","version":"1"}
{"action":{"distribution":{"allocations":[{"id":"npJT89Cbjr959SGMr4U8zw","policy":{"budget":"450000000000000000000","discount":0.5,"exclusions":[],"policyType":"RECENT"},"receipts":[{"amount":"450000000000000000000","id":"dO40pJDjmV59DjBrvIDocg"}]}],"credTimestamp":1651968000000,"id":"x4b08bQ2C1kwSGauXvNlKw"},"type":"DISTRIBUTE_GRAIN"},"ledgerTimestamp":1659233849797,"uuid":"xfxgSwZ1joDpdXTqFRQYtg","version":"1"}
{"action":{"distribution":{"allocations":[{"id":"VBcxqL3OvzTGoxNSGU6eNg","policy":{"budget":"450000000000000000000","discount":0.5,"exclusions":[],"policyType":"RECENT"},"receipts":[{"amount":"450000000000000000000","id":"dO40pJDjmV59DjBrvIDocg"}]}],"credTimestamp":1652572800000,"id":"J8Vv8L2PVlZ0MXes2dRz8g"},"type":"DISTRIBUTE_GRAIN"},"ledgerTimestamp":1659233849801,"uuid":"3Em2jrsKey4BD1vVRFJnuA","version":"1"}
{"action":{"distribution":{"allocations":[{"id":"8rejrbblAUk0Y15D9Z5UYA","policy":{"budget":"450000000000000000000","discount":0.5,"exclusions":[],"policyType":"RECENT"},"receipts":[{"amount":"450000000000000000000","id":"dO40pJDjmV59DjBrvIDocg"}]}],"credTimestamp":1653177600000,"id":"JIdUEAD4YnwjBvhWg51d8A"},"type":"DISTRIBUTE_GRAIN"},"ledgerTimestamp":1659233849804,"uuid":"4jGqbX9T3og8NFBjxYuJog","version":"1"}
{"action":{"distribution":{"allocations":[{"id":"HxhgZyXknjRfQjIB5qHbEQ","policy":{"budget":"450000000000000000000","discount":0.5,"exclusions":[],"policyType":"RECENT"},"receipts":[{"amount":"450000000000000000000","id":"dO40pJDjmV59DjBrvIDocg"}]}],"credTimestamp":1653782400000,"id":"TY0dG6TOVt1dgA6QDmUOqg"},"type":"DISTRIBUTE_GRAIN"},"ledgerTimestamp":1659233849807,"uuid":"uQpJzHzepmEPrcRQoMvqyg","version":"1"}
